SqlDB/__init__.py
sqldb-3.7.dist-info/LICENSE
sqldb-3.7.dist-info/METADATA
sqldb-3.7.dist-info/WHEEL
sqldb-3.7.dist-info/top_level.txt
sqldb-3.7.dist-info/RECORD
