Metadata-Version: 2.1
Name: sqldb
Version: 3.7
Summary: SQL Family DB handler
Home-page: https://github.com/kagepark/SqlDB
Author: Kage Park
License: MIT
Platform: UNKNOWN
Classifier: Programming Language :: Python :: 2
Classifier: Programming Language :: Python :: 3
Classifier: License :: OSI Approved :: MIT License
Classifier: Operating System :: OS Independent
License-File: LICENSE
